{
    "version": "4.5.6",
    "flags": {},
    "shapes": [
        {
            "label": "person",
            "points": [
                [
                    97.87545787545787,
                    184
                ],
                [
                    629.7892271662763,
                    1235.3709198813056
                ]
            ],
            "group_id": null,
            "shape_type": "rectangle",
            "flags": {}
        },
        {
            "label": "L-pi-1",
            "points": [
                [
                    448.66468842729967,
                    1175.3709198813056
                ]
            ],
            "group_id": null,
            "shape_type": "point",
            "flags": {}
        },
        {
            "label": "L-pi-2",
            "points": [
                [
                    441.5472779369627,
                    1150.1432664756446
                ]
            ],
            "group_id": null,
            "shape_type": "point",
            "flags": {}
        },
        {
            "label": "L-pi-3",
            "points": [
                [
                    446.7775467775467,
                    1059.6673596673595
                ]
            ],
            "group_id": null,
            "shape_type": "point",
            "flags": {}
        },
        {
            "label": "L-pi-4",
            "points": [
                [
                    440.7523510971787,
                    1019.7492163009405
                ]
            ],
            "group_id": null,
            "shape_type": "point",
            "flags": {}
        },
        {
            "label": "L-pi-5",
            "points": [
                [
                    431.4102564102564,
                    949.5726495726497
                ]
            ],
            "group_id": null,
            "shape_type": "point",
            "flags": {}
        },
        {
            "label": "L-pi-6",
            "points": [
                [
                    425.42735042735046,
                    905.982905982906
                ]
            ],
            "group_id": null,
            "shape_type": "point",
            "flags": {}
        },
        {
            "label": "L-pi-7",
            "points": [
                [
                    414.10256410256414,
                    861.3247863247864
                ]
            ],
            "group_id": null,
            "shape_type": "point",
            "flags": {}
        },
        {
            "label": "L-pi-8",
            "points": [
                [
                    423.9130434782609,
                    731.7934782608695
                ]
            ],
            "group_id": null,
            "shape_type": "point",
            "flags": {}
        },
        {
            "label": "L-pi-9",
            "points": [
                [
                    428.1789292259454,
                    649.6025620202912
                ]
            ],
            "group_id": null,
            "shape_type": "point",
            "flags": {}
        },
        {
            "label": "L-pi-10",
            "points": [
                [
                    416.33554083885207,
                    494.0397350993378
                ]
            ],
            "group_id": null,
            "shape_type": "point",
            "flags": {}
        },
        {
            "label": "L-pi-11",
            "points": [
                [
                    422.81879194630875,
                    474.4966442953021
                ]
            ],
            "group_id": null,
            "shape_type": "point",
            "flags": {}
        },
        {
            "label": "L-pi-12",
            "points": [
                [
                    417.5824175824176,
                    434.4322344322345
                ]
            ],
            "group_id": null,
            "shape_type": "point",
            "flags": {}
        },
        {
            "label": "R-pi-1",
            "points": [
                [
                    299.76525821596243,
                    1174.1784037558687
                ]
            ],
            "group_id": null,
            "shape_type": "point",
            "flags": {}
        },
        {
            "label": "R-pi-2",
            "points": [
                [
                    309.38967136150234,
                    1149.2957746478874
                ]
            ],
            "group_id": null,
            "shape_type": "point",
            "flags": {}
        },
        {
            "label": "R-pi-3",
            "points": [
                [
                    307.3741007194244,
                    1060.251798561151
                ]
            ],
            "group_id": null,
            "shape_type": "point",
            "flags": {}
        },
        {
            "label": "R-pi-4",
            "points": [
                [
                    312.5391849529781,
                    1019.7492163009405
                ]
            ],
            "group_id": null,
            "shape_type": "point",
            "flags": {}
        },
        {
            "label": "R-pi-5",
            "points": [
                [
                    323.8244514106583,
                    948.58934169279
                ]
            ],
            "group_id": null,
            "shape_type": "point",
            "flags": {}
        },
        {
            "label": "R-pi-6",
            "points": [
                [
                    330.12820512820514,
                    906.6239316239316
                ]
            ],
            "group_id": null,
            "shape_type": "point",
            "flags": {}
        },
        {
            "label": "R-pi-7",
            "points": [
                [
                    336.53846153846155,
                    863.2478632478633
                ]
            ],
            "group_id": null,
            "shape_type": "point",
            "flags": {}
        },
        {
            "label": "R-pi-8",
            "points": [
                [
                    324.41846765047126,
                    740.2390400033879
                ]
            ],
            "group_id": null,
            "shape_type": "point",
            "flags": {}
        },
        {
            "label": "R-pi-9",
            "points": [
                [
                    320.21832058537683,
                    661.6883264650799
                ]
            ],
            "group_id": null,
            "shape_type": "point",
            "flags": {}
        },
        {
            "label": "R-pi-10",
            "points": [
                [
                    309.9776403872345,
                    501.56241282068356
                ]
            ],
            "group_id": null,
            "shape_type": "point",
            "flags": {}
        },
        {
            "label": "R-pi-11",
            "points": [
                [
                    298.6500747320388,
                    484.7421846660626
                ]
            ],
            "group_id": null,
            "shape_type": "point",
            "flags": {}
        },
        {
            "label": "R-pi-12",
            "points": [
                [
                    303.6144578313253,
                    443.07228915662654
                ]
            ],
            "group_id": null,
            "shape_type": "point",
            "flags": {}
        },
        {
            "label": "R-xinbao-1",
            "points": [
                [
                    298.8226636680699,
                    484.7301160719892
                ]
            ],
            "group_id": null,
            "shape_type": "point",
            "flags": {}
        },
        {
            "label": "R-xinbao-2",
            "points": [
                [
                    271.0843373493976,
                    446.38554216867465
                ]
            ],
            "group_id": null,
            "shape_type": "point",
            "flags": {}
        },
        {
            "label": "R-xinbao-3",
            "points": [
                [
                    262.751677852349,
                    490.93959731543623
                ]
            ],
            "group_id": null,
            "shape_type": "point",
            "flags": {}
        },
        {
            "label": "R-xinbao-4",
            "points": [
                [
                    255.81395348837208,
                    547.3572938689217
                ]
            ],
            "group_id": null,
            "shape_type": "point",
            "flags": {}
        },
        {
            "label": "R-xinbao-5",
            "points": [
                [
                    202.45398773006136,
                    654.3967280163599
                ]
            ],
            "group_id": null,
            "shape_type": "point",
            "flags": {}
        },
        {
            "label": "R-xinbao-6",
            "points": [
                [
                    192.43353783231086,
                    684.8670756646217
                ]
            ],
            "group_id": null,
            "shape_type": "point",
            "flags": {}
        },
        {
            "label": "R-xinbao-7",
            "points": [
                [
                    176.8916155419223,
                    732.3108384458078
                ]
            ],
            "group_id": null,
            "shape_type": "point",
            "flags": {}
        },
        {
            "label": "R-xinbao-8",
            "points": [
                [
                    195.09202453987731,
                    701.8404907975461
                ]
            ],
            "group_id": null,
            "shape_type": "point",
            "flags": {}
        },
        {
            "label": "R-xinbao-9",
            "points": [
                [
                    190.79754601226995,
                    732.1063394683027
                ]
            ],
            "group_id": null,
            "shape_type": "point",
            "flags": {}
        },
        {
            "label": "L-xinbao-1",
            "points": [
                [
                    423.1543624161074,
                    474.4966442953021
                ]
            ],
            "group_id": null,
            "shape_type": "point",
            "flags": {}
        },
        {
            "label": "L-xinbao-2",
            "points": [
                [
                    446.15384615384613,
                    431.86813186813185
                ]
            ],
            "group_id": null,
            "shape_type": "point",
            "flags": {}
        },
        {
            "label": "L-xinbao-3",
            "points": [
                [
                    464.4391408114558,
                    473.2696897374701
                ]
            ],
            "group_id": null,
            "shape_type": "point",
            "flags": {}
        },
        {
            "label": "L-xinbao-4",
            "points": [
                [
                    477.82805429864254,
                    529.4117647058823
                ]
            ],
            "group_id": null,
            "shape_type": "point",
            "flags": {}
        },
        {
            "label": "L-xinbao-5",
            "points": [
                [
                    526.8482490272373,
                    635.6679636835279
                ]
            ],
            "group_id": null,
            "shape_type": "point",
            "flags": {}
        },
        {
            "label": "L-xinbao-6",
            "points": [
                [
                    540.5152224824355,
                    662.9976580796252
                ]
            ],
            "group_id": null,
            "shape_type": "point",
            "flags": {}
        },
        {
            "label": "L-xinbao-7",
            "points": [
                [
                    557.3770491803278,
                    712.1779859484777
                ]
            ],
            "group_id": null,
            "shape_type": "point",
            "flags": {}
        },
        {
            "label": "L-xinbao-8",
            "points": [
                [
                    535.5971896955502,
                    681.2646370023418
                ]
            ],
            "group_id": null,
            "shape_type": "point",
            "flags": {}
        },
        {
            "label": "L-xinbao-9",
            "points": [
                [
                    539.3442622950819,
                    711.943793911007
                ]
            ],
            "group_id": null,
            "shape_type": "point",
            "flags": {}
        },
        {
            "label": "L-wei-15",
            "points": [
                [
                    370.2631578947368,
                    415.2631578947369
                ]
            ],
            "group_id": null,
            "shape_type": "point",
            "flags": {}
        },
        {
            "label": "L-wei-16",
            "points": [
                [
                    383.9473684210526,
                    413.68421052631584
                ]
            ],
            "group_id": null,
            "shape_type": "point",
            "flags": {}
        },
        {
            "label": "L-wei-17",
            "points": [
                [
                    414.4295302013423,
                    475.5033557046979
                ]
            ],
            "group_id": null,
            "shape_type": "point",
            "flags": {}
        },
        {
            "label": "L-wei-18",
            "points": [
                [
                    401.32450331125824,
                    502.2075055187638
                ]
            ],
            "group_id": null,
            "shape_type": "point",
            "flags": {}
        },
        {
            "label": "L-wei-19",
            "points": [
                [
                    408.32186442755074,
                    598.2333780939535
                ]
            ],
            "group_id": null,
            "shape_type": "point",
            "flags": {}
        },
        {
            "label": "L-wei-20",
            "points": [
                [
                    409.5723014256619,
                    621.1812627291242
                ]
            ],
            "group_id": null,
            "shape_type": "point",
            "flags": {}
        },
        {
            "label": "L-wei-21",
            "points": [
                [
                    428.1789292259454,
                    649.6025620202912
                ]
            ],
            "group_id": null,
            "shape_type": "point",
            "flags": {}
        },
        {
            "label": "L-wei-22",
            "points": [
                [
                    445.45454545454544,
                    692.490118577075
                ]
            ],
            "group_id": null,
            "shape_type": "point",
            "flags": {}
        },
        {
            "label": "L-wei-23",
            "points": [
                [
                    447.45762711864404,
                    729.4915254237287
                ]
            ],
            "group_id": null,
            "shape_type": "point",
            "flags": {}
        },
        {
            "label": "L-wei-24",
            "points": [
                [
                    438.2478632478633,
                    859.8290598290599
                ]
            ],
            "group_id": null,
            "shape_type": "point",
            "flags": {}
        },
        {
            "label": "L-wei-25",
            "points": [
                [
                    447.00854700854705,
                    904.2735042735043
                ]
            ],
            "group_id": null,
            "shape_type": "point",
            "flags": {}
        },
        {
            "label": "L-wei-26",
            "points": [
                [
                    454.27350427350433,
                    949.7863247863248
                ]
            ],
            "group_id": null,
            "shape_type": "point",
            "flags": {}
        },
        {
            "label": "L-wei-27",
            "points": [
                [
                    453.014553014553,
                    1059.8752598752599
                ]
            ],
            "group_id": null,
            "shape_type": "point",
            "flags": {}
        },
        {
            "label": "L-wei-28",
            "points": [
                [
                    460.6356968215159,
                    1153.5452322738386
                ]
            ],
            "group_id": null,
            "shape_type": "point",
            "flags": {}
        },
        {
            "label": "L-wei-29",
            "points": [
                [
                    459.043659043659,
                    1060.08316008316
                ]
            ],
            "group_id": null,
            "shape_type": "point",
            "flags": {}
        },
        {
            "label": "L-wei-30",
            "points": [
                [
                    465.52567237163817,
                    1146.9437652811737
                ]
            ],
            "group_id": null,
            "shape_type": "point",
            "flags": {}
        },
        {
            "label": "R-wei-15",
            "points": [
                [
                    344.2771084337349,
                    418.07228915662654
                ]
            ],
            "group_id": null,
            "shape_type": "point",
            "flags": {}
        },
        {
            "label": "R-wei-16",
            "points": [
                [
                    331.0240963855421,
                    420.18072289156623
                ]
            ],
            "group_id": null,
            "shape_type": "point",
            "flags": {}
        },
        {
            "label": "R-wei-17",
            "points": [
                [
                    305.37142705712307,
                    484.1234329788905
                ]
            ],
            "group_id": null,
            "shape_type": "point",
            "flags": {}
        },
        {
            "label": "R-wei-18",
            "points": [
                [
                    327.8523489932886,
                    507.04697986577185
                ]
            ],
            "group_id": null,
            "shape_type": "point",
            "flags": {}
        },
        {
            "label": "R-wei-19",
            "points": [
                [
                    334.41955193482687,
                    606.3136456211812
                ]
            ],
            "group_id": null,
            "shape_type": "point",
            "flags": {}
        },
        {
            "label": "R-wei-20",
            "points": [
                [
                    336.65987780040734,
                    625.254582484725
                ]
            ],
            "group_id": null,
            "shape_type": "point",
            "flags": {}
        },
        {
            "label": "R-wei-21",
            "points": [
                [
                    320.508310134871,
                    661.668048420387
                ]
            ],
            "group_id": null,
            "shape_type": "point",
            "flags": {}
        },
        {
            "label": "R-wei-22",
            "points": [
                [
                    303.0508474576271,
                    700.3389830508474
                ]
            ],
            "group_id": null,
            "shape_type": "point",
            "flags": {}
        },
        {
            "label": "R-wei-23",
            "points": [
                [
                    300.395256916996,
                    739.5256916996046
                ]
            ],
            "group_id": null,
            "shape_type": "point",
            "flags": {}
        },
        {
            "label": "R-wei-24",
            "points": [
                [
                    311.7521367521368,
                    863.6752136752137
                ]
            ],
            "group_id": null,
            "shape_type": "point",
            "flags": {}
        },
        {
            "label": "R-wei-25",
            "points": [
                [
                    306.83760683760687,
                    906.4102564102565
                ]
            ],
            "group_id": null,
            "shape_type": "point",
            "flags": {}
        },
        {
            "label": "R-wei-26",
            "points": [
                [
                    300.0,
                    948.931623931624
                ]
            ],
            "group_id": null,
            "shape_type": "point",
            "flags": {}
        },
        {
            "label": "R-wei-27",
            "points": [
                [
                    301.6187050359712,
                    1060.4316546762589
                ]
            ],
            "group_id": null,
            "shape_type": "point",
            "flags": {}
        },
        {
            "label": "R-wei-28",
            "points": [
                [
                    289.906103286385,
                    1153.9906103286385
                ]
            ],
            "group_id": null,
            "shape_type": "point",
            "flags": {}
        },
        {
            "label": "R-wei-29",
            "points": [
                [
                    294.9640287769784,
                    1060.4316546762589
                ]
            ],
            "group_id": null,
            "shape_type": "point",
            "flags": {}
        },
        {
            "label": "R-wei-30",
            "points": [
                [
                    285.6807511737089,
                    1146.4788732394368
                ]
            ],
            "group_id": null,
            "shape_type": "point",
            "flags": {}
        },
        {
            "label": "L-fei-1",
            "points": [
                [
                    415.01831501831504,
                    423.4432234432235
                ]
            ],
            "group_id": null,
            "shape_type": "point",
            "flags": {}
        },
        {
            "label": "L-fei-2",
            "points": [
                [
                    414.7368421052631,
                    415.52631578947364
                ]
            ],
            "group_id": null,
            "shape_type": "point",
            "flags": {}
        },
        {
            "label": "L-fei-3",
            "points": [
                [
                    449.4736842105263,
                    411.31578947368416
                ]
            ],
            "group_id": null,
            "shape_type": "point",
            "flags": {}
        },
        {
            "label": "L-fei-4",
            "points": [
                [
                    473.74701670644384,
                    471.1217183770882
                ]
            ],
            "group_id": null,
            "shape_type": "point",
            "flags": {}
        },
        {
            "label": "L-fei-5",
            "points": [
                [
                    488.2352941176471,
                    528.0542986425339
                ]
            ],
            "group_id": null,
            "shape_type": "point",
            "flags": {}
        },
        {
            "label": "L-fei-6",
            "points": [
                [
                    532.7868852459015,
                    633.4894613583137
                ]
            ],
            "group_id": null,
            "shape_type": "point",
            "flags": {}
        },
        {
            "label": "L-fei-7",
            "points": [
                [
                    551.9906323185011,
                    645.19906323185
                ]
            ],
            "group_id": null,
            "shape_type": "point",
            "flags": {}
        },
        {
            "label": "L-fei-8",
            "points": [
                [
                    569.7892271662763,
                    658.7822014051521
                ]
            ],
            "group_id": null,
            "shape_type": "point",
            "flags": {}
        },
        {
            "label": "R-fei-1",
            "points": [
                [
                    302.71084337349396,
                    431.92771084337346
                ]
            ],
            "group_id": null,
            "shape_type": "point",
            "flags": {}
        },
        {
            "label": "R-fei-2",
            "points": [
                [
                    301.5060240963855,
                    424.0963855421687
                ]
            ],
            "group_id": null,
            "shape_type": "point",
            "flags": {}
        },
        {
            "label": "R-fei-3",
            "points": [
                [
                    268.0722891566265,
                    428.61445783132524
                ]
            ],
            "group_id": null,
            "shape_type": "point",
            "flags": {}
        },
        {
            "label": "R-fei-4",
            "points": [
                [
                    252.01342281879195,
                    491.61073825503354
                ]
            ],
            "group_id": null,
            "shape_type": "point",
            "flags": {}
        },
        {
            "label": "R-fei-5",
            "points": [
                [
                    245.3020134228188,
                    547.3154362416108
                ]
            ],
            "group_id": null,
            "shape_type": "point",
            "flags": {}
        },
        {
            "label": "R-fei-6",
            "points": [
                [
                    196.11451942740288,
                    653.1697341513293
                ]
            ],
            "group_id": null,
            "shape_type": "point",
            "flags": {}
        },
        {
            "label": "R-fei-7",
            "points": [
                [
                    183.15018315018315,
                    662.6373626373627
                ]
            ],
            "group_id": null,
            "shape_type": "point",
            "flags": {}
        },
        {
            "label": "R-fei-8",
            "points": [
                [
                    157.87545787545787,
                    677.6556776556777
                ]
            ],
            "group_id": null,
            "shape_type": "point",
            "flags": {}
        }
    ],
    "imagePath": "m_up_nei_20221230093955060.jpg",
    "imageData": null,
    "imageHeight": 1280,
    "imageWidth": 720
}