{
  "version": "4.5.6", 
  "flags": {}, 
  "shapes": [
    {
      "label": "person", 
      "points": [
        [
          60, 
          120
        ], 
        [
          1096, 
          625
        ]
      ], 
      "group_id": null, 
      "shape_type": "rectangle", 
      "flags": {}
    }, 
    {
      "label": "L-sanjiao-1", 
      "points": [
        [
          566.2542955326461, 
          239.86254295532646
        ]
      ], 
      "group_id": null, 
      "shape_type": "point", 
      "flags": {}
    }, 
    {
      "label": "L-sanjiao-2", 
      "points": [
        [
          601.6494845360825, 
          247.07903780068727
        ]
      ], 
      "group_id": null, 
      "shape_type": "point", 
      "flags": {}
    }, 
    {
      "label": "L-sanjiao-3", 
      "points": [
        [
          629.767441860465, 
          246.27906976744188
        ]
      ], 
      "group_id": null, 
      "shape_type": "point", 
      "flags": {}
    }, 
    {
      "label": "L-sanjiao-4", 
      "points": [
        [
          724.7257383966245, 
          275.66807313642755
        ]
      ], 
      "group_id": null, 
      "shape_type": "point", 
      "flags": {}
    }, 
    {
      "label": "L-sanjiao-5", 
      "points": [
        [
          764.7583643122676, 
          275.2788104089219
        ]
      ], 
      "group_id": null, 
      "shape_type": "point", 
      "flags": {}
    }, 
    {
      "label": "L-sanjiao-6", 
      "points": [
        [
          814.7583643122676, 
          280.1115241635688
        ]
      ], 
      "group_id": null, 
      "shape_type": "point", 
      "flags": {}
    }, 
    {
      "label": "L-sanjiao-7", 
      "points": [
        [
          830.0, 
          289.7177419354839
        ]
      ], 
      "group_id": null, 
      "shape_type": "point", 
      "flags": {}
    }, 
    {
      "label": "L-sanjiao-8", 
      "points": [
        [
          844.878892733564, 
          319.5501730103806
        ]
      ], 
      "group_id": null, 
      "shape_type": "point", 
      "flags": {}
    }, 
    {
      "label": "L-sanjiao-9", 
      "points": [
        [
          859.4683683933603, 
          355.6009831726277
        ]
      ], 
      "group_id": null, 
      "shape_type": "point", 
      "flags": {}
    }, 
    {
      "label": "R-sanjiao-1", 
      "points": [
        [
          566.2542955326461, 
          503.0927835051546
        ]
      ], 
      "group_id": null, 
      "shape_type": "point", 
      "flags": {}
    }, 
    {
      "label": "R-sanjiao-2", 
      "points": [
        [
          605.085910652921, 
          499.3127147766323
        ]
      ], 
      "group_id": null, 
      "shape_type": "point", 
      "flags": {}
    }, 
    {
      "label": "R-sanjiao-3", 
      "points": [
        [
          631.9101123595506, 
          496.62921348314603
        ]
      ], 
      "group_id": null, 
      "shape_type": "point", 
      "flags": {}
    }, 
    {
      "label": "R-sanjiao-4", 
      "points": [
        [
          732.8028933092224, 
          460.0361663652803
        ]
      ], 
      "group_id": null, 
      "shape_type": "point", 
      "flags": {}
    }, 
    {
      "label": "R-sanjiao-5", 
      "points": [
        [
          764.9442379182155, 
          455.7620817843866
        ]
      ], 
      "group_id": null, 
      "shape_type": "point", 
      "flags": {}
    }, 
    {
      "label": "R-sanjiao-6", 
      "points": [
        [
          814.5058626465661, 
          453.27638190954775
        ]
      ], 
      "group_id": null, 
      "shape_type": "point", 
      "flags": {}
    }, 
    {
      "label": "R-sanjiao-7", 
      "points": [
        [
          829.6437054631829, 
          443.3681710213777
        ]
      ], 
      "group_id": null, 
      "shape_type": "point", 
      "flags": {}
    }, 
    {
      "label": "R-sanjiao-8", 
      "points": [
        [
          844.973544973545, 
          420.10582010582004
        ]
      ], 
      "group_id": null, 
      "shape_type": "point", 
      "flags": {}
    }, 
    {
      "label": "R-sanjiao-9", 
      "points": [
        [
          859.8955181751328, 
          375.35284664943566
        ]
      ], 
      "group_id": null, 
      "shape_type": "point", 
      "flags": {}
    }, 
    {
      "label": "L-pangguang-9", 
      "points": [
        [
          904.6, 
          355.0
        ]
      ], 
      "group_id": null, 
      "shape_type": "point", 
      "flags": {}
    }, 
    {
      "label": "L-pangguang-10", 
      "points": [
        [
          859.7488761382901, 
          355.47276360937065
        ]
      ], 
      "group_id": null, 
      "shape_type": "point", 
      "flags": {}
    }, 
    {
      "label": "L-pangguang-11", 
      "points": [
        [
          844.9499015585075, 
          350.0666409826388
        ]
      ], 
      "group_id": null, 
      "shape_type": "point", 
      "flags": {}
    }, 
    {
      "label": "L-pangguang-12", 
      "points": [
        [
          604.6768507638072, 
          341.1280846063455
        ]
      ], 
      "group_id": null, 
      "shape_type": "point", 
      "flags": {}
    }, 
    {
      "label": "L-pangguang-13", 
      "points": [
        [
          634.3103448275862, 
          351.7241379310345
        ]
      ], 
      "group_id": null, 
      "shape_type": "point", 
      "flags": {}
    }, 
    {
      "label": "L-pangguang-14", 
      "points": [
        [
          594.6551724137931, 
          351.3793103448276
        ]
      ], 
      "group_id": null, 
      "shape_type": "point", 
      "flags": {}
    }, 
    {
      "label": "L-pangguang-15", 
      "points": [
        [
          574.4, 
          336.2
        ]
      ], 
      "group_id": null, 
      "shape_type": "point", 
      "flags": {}
    }, 
    {
      "label": "L-pangguang-16", 
      "points": [
        [
          429.6981891348088, 
          308.14889336016097
        ]
      ], 
      "group_id": null, 
      "shape_type": "point", 
      "flags": {}
    }, 
    {
      "label": "L-pangguang-17", 
      "points": [
        [
          429.84423676012455, 
          319.9376947040499
        ]
      ], 
      "group_id": null, 
      "shape_type": "point", 
      "flags": {}
    }, 
    {
      "label": "L-pangguang-18", 
      "points": [
        [
          904.5, 
          355.2
        ]
      ], 
      "group_id": null, 
      "shape_type": "point", 
      "flags": {}
    }, 
    {
      "label": "L-pangguang-19", 
      "points": [
        [
          864.4444444444443, 
          345.1851851851852
        ]
      ], 
      "group_id": null, 
      "shape_type": "point", 
      "flags": {}
    }, 
    {
      "label": "L-pangguang-20", 
      "points": [
        [
          844.3598615916956, 
          319.72318339100343
        ]
      ], 
      "group_id": null, 
      "shape_type": "point", 
      "flags": {}
    }, 
    {
      "label": "L-pangguang-21", 
      "points": [
        [
          685.2410901467506, 
          324.3186582809224
        ]
      ], 
      "group_id": null, 
      "shape_type": "point", 
      "flags": {}
    }, 
    {
      "label": "L-pangguang-22", 
      "points": [
        [
          664.6960167714885, 
          319.70649895178195
        ]
      ], 
      "group_id": null, 
      "shape_type": "point", 
      "flags": {}
    }, 
    {
      "label": "L-pangguang-23", 
      "points": [
        [
          574.9152542372882, 
          302.03389830508473
        ]
      ], 
      "group_id": null, 
      "shape_type": "point", 
      "flags": {}
    }, 
    {
      "label": "L-pangguang-24", 
      "points": [
        [
          359.79274611398966, 
          315.8894645941278
        ]
      ], 
      "group_id": null, 
      "shape_type": "point", 
      "flags": {}
    }, 
    {
      "label": "R-pangguang-9", 
      "points": [
        [
          904.5, 
          380.2
        ]
      ], 
      "group_id": null, 
      "shape_type": "point", 
      "flags": {}
    }, 
    {
      "label": "R-pangguang-10", 
      "points": [
        [
          860.037881540805, 
          375.3578180877124
        ]
      ], 
      "group_id": null, 
      "shape_type": "point", 
      "flags": {}
    }, 
    {
      "label": "R-pangguang-11", 
      "points": [
        [
          844.320987654321, 
          380.24691358024694
        ]
      ], 
      "group_id": null, 
      "shape_type": "point", 
      "flags": {}
    }, 
    {
      "label": "R-pangguang-12", 
      "points": [
        [
          605.0, 
          391.4
        ]
      ], 
      "group_id": null, 
      "shape_type": "point", 
      "flags": {}
    }, 
    {
      "label": "R-pangguang-13", 
      "points": [
        [
          634.75910693302, 
          381.551116333725
        ]
      ], 
      "group_id": null, 
      "shape_type": "point", 
      "flags": {}
    }, 
    {
      "label": "R-pangguang-14", 
      "points": [
        [
          594.7, 
          381.4
        ]
      ], 
      "group_id": null, 
      "shape_type": "point", 
      "flags": {}
    }, 
    {
      "label": "R-pangguang-15", 
      "points": [
        [
          574.8, 
          396.5
        ]
      ], 
      "group_id": null, 
      "shape_type": "point", 
      "flags": {}
    }, 
    {
      "label": "R-pangguang-16", 
      "points": [
        [
          429.75961538461536, 
          432.21153846153845
        ]
      ], 
      "group_id": null, 
      "shape_type": "point", 
      "flags": {}
    }, 
    {
      "label": "R-pangguang-17", 
      "points": [
        [
          429.737532808399, 
          420.0787401574803
        ]
      ], 
      "group_id": null, 
      "shape_type": "point", 
      "flags": {}
    }, 
    {
      "label": "R-pangguang-18", 
      "points": [
        [
          904.8, 
          380.1
        ]
      ], 
      "group_id": null, 
      "shape_type": "point", 
      "flags": {}
    }, 
    {
      "label": "R-pangguang-19", 
      "points": [
        [
          864.8148148148148, 
          384.5679012345679
        ]
      ], 
      "group_id": null, 
      "shape_type": "point", 
      "flags": {}
    }, 
    {
      "label": "R-pangguang-20", 
      "points": [
        [
          844.5502645502646, 
          420.21164021164014
        ]
      ], 
      "group_id": null, 
      "shape_type": "point", 
      "flags": {}
    }, 
    {
      "label": "R-pangguang-21", 
      "points": [
        [
          684.6121593291405, 
          404.1928721174004
        ]
      ], 
      "group_id": null, 
      "shape_type": "point", 
      "flags": {}
    }, 
    {
      "label": "R-pangguang-22", 
      "points": [
        [
          664.6960167714885, 
          409.01467505241084
        ]
      ], 
      "group_id": null, 
      "shape_type": "point", 
      "flags": {}
    }, 
    {
      "label": "R-pangguang-23", 
      "points": [
        [
          574.406779661017, 
          430.1694915254237
        ]
      ], 
      "group_id": null, 
      "shape_type": "point", 
      "flags": {}
    }, 
    {
      "label": "R-pangguang-24", 
      "points": [
        [
          359.447322970639, 
          426.94300518134713
        ]
      ], 
      "group_id": null, 
      "shape_type": "point", 
      "flags": {}
    }, 
    {
      "label": "R-pangguang-7", 
      "points": [
        [
          970.1, 
          380.1
        ]
      ], 
      "group_id": null, 
      "shape_type": "point", 
      "flags": {}
    }, 
    {
      "label": "R-pangguang-30", 
      "points": [
        [
          954.9, 
          379.9
        ]
      ], 
      "group_id": null, 
      "shape_type": "point", 
      "flags": {}
    }, 
    {
      "label": "R-pangguang-8", 
      "points": [
        [
          939.8, 
          380.2
        ]
      ], 
      "group_id": null, 
      "shape_type": "point", 
      "flags": {}
    }, 
    {
      "label": "L-pangguang-7", 
      "points": [
        [
          970.6, 
          355.1
        ]
      ], 
      "group_id": null, 
      "shape_type": "point", 
      "flags": {}
    }, 
    {
      "label": "L-pangguang-30", 
      "points": [
        [
          954.8, 
          355.0
        ]
      ], 
      "group_id": null, 
      "shape_type": "point", 
      "flags": {}
    }, 
    {
      "label": "L-pangguang-8", 
      "points": [
        [
          940.6410256410256, 
          355.12820512820514
        ]
      ], 
      "group_id": null, 
      "shape_type": "point", 
      "flags": {}
    }
  ], 
  "imagePath": "m_down_wai_20221230133621668.jpg", 
  "imageData": null, 
  "imageHeight": 720, 
  "imageWidth": 1280
}