{
  "version": "4.5.6", 
  "flags": {}, 
  "shapes": [
    {
      "label": "person", 
      "points": [
        [
          60, 
          120
        ], 
        [
          1096, 
          625
        ]
      ], 
      "group_id": null, 
      "shape_type": "rectangle", 
      "flags": {}
    }, 
    {
      "label": "L-sanjiao-1", 
      "points": [
        [
          514.6311475409835, 
          266.8032786885246
        ]
      ], 
      "group_id": null, 
      "shape_type": "point", 
      "flags": {}
    }, 
    {
      "label": "L-sanjiao-2", 
      "points": [
        [
          550.6967213114754, 
          263.7295081967213
        ]
      ], 
      "group_id": null, 
      "shape_type": "point", 
      "flags": {}
    }, 
    {
      "label": "L-sanjiao-3", 
      "points": [
        [
          576.2765957446809, 
          258.24468085106383
        ]
      ], 
      "group_id": null, 
      "shape_type": "point", 
      "flags": {}
    }, 
    {
      "label": "L-sanjiao-4", 
      "points": [
        [
          664.5744680851064, 
          282.1808510638298
        ]
      ], 
      "group_id": null, 
      "shape_type": "point", 
      "flags": {}
    }, 
    {
      "label": "L-sanjiao-5", 
      "points": [
        [
          719.5705521472393, 
          289.57055214723925
        ]
      ], 
      "group_id": null, 
      "shape_type": "point", 
      "flags": {}
    }, 
    {
      "label": "L-sanjiao-6", 
      "points": [
        [
          764.6835443037975, 
          290.0
        ]
      ], 
      "group_id": null, 
      "shape_type": "point", 
      "flags": {}
    }, 
    {
      "label": "L-sanjiao-7", 
      "points": [
        [
          779.620253164557, 
          300.0
        ]
      ], 
      "group_id": null, 
      "shape_type": "point", 
      "flags": {}
    }, 
    {
      "label": "L-sanjiao-8", 
      "points": [
        [
          794.5719489981785, 
          324.59016393442624
        ]
      ], 
      "group_id": null, 
      "shape_type": "point", 
      "flags": {}
    }, 
    {
      "label": "L-sanjiao-9", 
      "points": [
        [
          809.2654028436018, 
          365.9952606635071
        ]
      ], 
      "group_id": null, 
      "shape_type": "point", 
      "flags": {}
    }, 
    {
      "label": "R-sanjiao-1", 
      "points": [
        [
          514.5890410958904, 
          481.5068493150685
        ]
      ], 
      "group_id": null, 
      "shape_type": "point", 
      "flags": {}
    }, 
    {
      "label": "R-sanjiao-2", 
      "points": [
        [
          542.6712328767123, 
          477.7397260273973
        ]
      ], 
      "group_id": null, 
      "shape_type": "point", 
      "flags": {}
    }, 
    {
      "label": "R-sanjiao-3", 
      "points": [
        [
          575.068493150685, 
          480.8219178082192
        ]
      ], 
      "group_id": null, 
      "shape_type": "point", 
      "flags": {}
    }, 
    {
      "label": "R-sanjiao-4", 
      "points": [
        [
          669.5705521472393, 
          463.19018404907973
        ]
      ], 
      "group_id": null, 
      "shape_type": "point", 
      "flags": {}
    }, 
    {
      "label": "R-sanjiao-5", 
      "points": [
        [
          719.7205588822355, 
          463.2734530938124
        ]
      ], 
      "group_id": null, 
      "shape_type": "point", 
      "flags": {}
    }, 
    {
      "label": "R-sanjiao-6", 
      "points": [
        [
          764.4221105527638, 
          460.8040201005025
        ]
      ], 
      "group_id": null, 
      "shape_type": "point", 
      "flags": {}
    }, 
    {
      "label": "R-sanjiao-7", 
      "points": [
        [
          779.4708994708996, 
          450.2645502645502
        ]
      ], 
      "group_id": null, 
      "shape_type": "point", 
      "flags": {}
    }, 
    {
      "label": "R-sanjiao-8", 
      "points": [
        [
          794.5719489981785, 
          429.3260473588342
        ]
      ], 
      "group_id": null, 
      "shape_type": "point", 
      "flags": {}
    }, 
    {
      "label": "R-sanjiao-9", 
      "points": [
        [
          809.7, 
          386.0
        ]
      ], 
      "group_id": null, 
      "shape_type": "point", 
      "flags": {}
    }, 
    {
      "label": "L-pangguang-9", 
      "points": [
        [
          838.2, 
          363.4
        ]
      ], 
      "group_id": null, 
      "shape_type": "point", 
      "flags": {}
    }, 
    {
      "label": "L-pangguang-10", 
      "points": [
        [
          809.1469194312796, 
          366.9431279620853
        ]
      ], 
      "group_id": null, 
      "shape_type": "point", 
      "flags": {}
    }, 
    {
      "label": "L-pangguang-11", 
      "points": [
        [
          794.6, 
          362.0
        ]
      ], 
      "group_id": null, 
      "shape_type": "point", 
      "flags": {}
    }, 
    {
      "label": "L-pangguang-12", 
      "points": [
        [
          559.4117647058823, 
          351.1029411764706
        ]
      ], 
      "group_id": null, 
      "shape_type": "point", 
      "flags": {}
    }, 
    {
      "label": "L-pangguang-13", 
      "points": [
        [
          594.5833333333334, 
          361.51960784313724
        ]
      ], 
      "group_id": null, 
      "shape_type": "point", 
      "flags": {}
    }, 
    {
      "label": "L-pangguang-14", 
      "points": [
        [
          549.4852941176471, 
          361.1519607843137
        ]
      ], 
      "group_id": null, 
      "shape_type": "point", 
      "flags": {}
    }, 
    {
      "label": "L-pangguang-15", 
      "points": [
        [
          514.8595213319459, 
          346.82622268470345
        ]
      ], 
      "group_id": null, 
      "shape_type": "point", 
      "flags": {}
    }, 
    {
      "label": "L-pangguang-16", 
      "points": [
        [
          384.0767386091127, 
          325.6594724220624
        ]
      ], 
      "group_id": null, 
      "shape_type": "point", 
      "flags": {}
    }, 
    {
      "label": "L-pangguang-17", 
      "points": [
        [
          384.5563549160671, 
          339.3285371702638
        ]
      ], 
      "group_id": null, 
      "shape_type": "point", 
      "flags": {}
    }, 
    {
      "label": "L-pangguang-18", 
      "points": [
        [
          838.1, 
          363.2
        ]
      ], 
      "group_id": null, 
      "shape_type": "point", 
      "flags": {}
    }, 
    {
      "label": "L-pangguang-19", 
      "points": [
        [
          814.7156398104265, 
          356.2796208530806
        ]
      ], 
      "group_id": null, 
      "shape_type": "point", 
      "flags": {}
    }, 
    {
      "label": "L-pangguang-20", 
      "points": [
        [
          794.936247723133, 
          324.77231329690346
        ]
      ], 
      "group_id": null, 
      "shape_type": "point", 
      "flags": {}
    }, 
    {
      "label": "L-pangguang-21", 
      "points": [
        [
          634.5, 
          334.75
        ]
      ], 
      "group_id": null, 
      "shape_type": "point", 
      "flags": {}
    }, 
    {
      "label": "L-pangguang-22", 
      "points": [
        [
          614.75, 
          330.0
        ]
      ], 
      "group_id": null, 
      "shape_type": "point", 
      "flags": {}
    }, 
    {
      "label": "L-pangguang-23", 
      "points": [
        [
          515.0785340314137, 
          313.8743455497382
        ]
      ], 
      "group_id": null, 
      "shape_type": "point", 
      "flags": {}
    }, 
    {
      "label": "L-pangguang-24", 
      "points": [
        [
          314.5323741007194, 
          329.9760191846523
        ]
      ], 
      "group_id": null, 
      "shape_type": "point", 
      "flags": {}
    }, 
    {
      "label": "R-pangguang-9", 
      "points": [
        [
          839.0, 
          387.1
        ]
      ], 
      "group_id": null, 
      "shape_type": "point", 
      "flags": {}
    }, 
    {
      "label": "R-pangguang-10", 
      "points": [
        [
          809.8, 
          386.1
        ]
      ], 
      "group_id": null, 
      "shape_type": "point", 
      "flags": {}
    }, 
    {
      "label": "R-pangguang-11", 
      "points": [
        [
          795.0, 
          391.4
        ]
      ], 
      "group_id": null, 
      "shape_type": "point", 
      "flags": {}
    }, 
    {
      "label": "R-pangguang-12", 
      "points": [
        [
          559.5343137254902, 
          403.55392156862746
        ]
      ], 
      "group_id": null, 
      "shape_type": "point", 
      "flags": {}
    }, 
    {
      "label": "R-pangguang-13", 
      "points": [
        [
          594.36962890625, 
          393.67730712890625
        ]
      ], 
      "group_id": null, 
      "shape_type": "point", 
      "flags": {}
    }, 
    {
      "label": "R-pangguang-14", 
      "points": [
        [
          549.4852941176471, 
          393.75
        ]
      ], 
      "group_id": null, 
      "shape_type": "point", 
      "flags": {}
    }, 
    {
      "label": "R-pangguang-15", 
      "points": [
        [
          514.8189415041783, 
          408.07799442896936
        ]
      ], 
      "group_id": null, 
      "shape_type": "point", 
      "flags": {}
    }, 
    {
      "label": "R-pangguang-16", 
      "points": [
        [
          384.0767386091127, 
          428.537170263789
        ]
      ], 
      "group_id": null, 
      "shape_type": "point", 
      "flags": {}
    }, 
    {
      "label": "R-pangguang-17", 
      "points": [
        [
          384.70000000000005, 
          412.6
        ]
      ], 
      "group_id": null, 
      "shape_type": "point", 
      "flags": {}
    }, 
    {
      "label": "R-pangguang-18", 
      "points": [
        [
          838.9, 
          387.0
        ]
      ], 
      "group_id": null, 
      "shape_type": "point", 
      "flags": {}
    }, 
    {
      "label": "R-pangguang-19", 
      "points": [
        [
          814.5, 
          396.7
        ]
      ], 
      "group_id": null, 
      "shape_type": "point", 
      "flags": {}
    }, 
    {
      "label": "R-pangguang-20", 
      "points": [
        [
          794.7540983606557, 
          429.6903460837887
        ]
      ], 
      "group_id": null, 
      "shape_type": "point", 
      "flags": {}
    }, 
    {
      "label": "R-pangguang-21", 
      "points": [
        [
          635.5, 
          424.0
        ]
      ], 
      "group_id": null, 
      "shape_type": "point", 
      "flags": {}
    }, 
    {
      "label": "R-pangguang-22", 
      "points": [
        [
          616.0, 
          429.75
        ]
      ], 
      "group_id": null, 
      "shape_type": "point", 
      "flags": {}
    }, 
    {
      "label": "R-pangguang-23", 
      "points": [
        [
          514.6743295019156, 
          445.9770114942529
        ]
      ], 
      "group_id": null, 
      "shape_type": "point", 
      "flags": {}
    }, 
    {
      "label": "R-pangguang-24", 
      "points": [
        [
          314.2925659472422, 
          423.2613908872902
        ]
      ], 
      "group_id": null, 
      "shape_type": "point", 
      "flags": {}
    }, 
    {
      "label": "R-pangguang-7", 
      "points": [
        [
          906.9135802469136, 
          384.320987654321
        ]
      ], 
      "group_id": null, 
      "shape_type": "point", 
      "flags": {}
    }, 
    {
      "label": "R-pangguang-30", 
      "points": [
        [
          891.9753086419753, 
          384.5679012345679
        ]
      ], 
      "group_id": null, 
      "shape_type": "point", 
      "flags": {}
    }, 
    {
      "label": "R-pangguang-8", 
      "points": [
        [
          876.1728395061727, 
          385.1851851851852
        ]
      ], 
      "group_id": null, 
      "shape_type": "point", 
      "flags": {}
    }, 
    {
      "label": "L-pangguang-7", 
      "points": [
        [
          905.9259259259259, 
          358.16186556927295
        ]
      ], 
      "group_id": null, 
      "shape_type": "point", 
      "flags": {}
    }, 
    {
      "label": "L-pangguang-30", 
      "points": [
        [
          890.0, 
          358.8888888888889
        ]
      ], 
      "group_id": null, 
      "shape_type": "point", 
      "flags": {}
    }, 
    {
      "label": "L-pangguang-8", 
      "points": [
        [
          873.4156378600824, 
          360.7681755829904
        ]
      ], 
      "group_id": null, 
      "shape_type": "point", 
      "flags": {}
    }
  ], 
  "imagePath": "m_down_wai_20221229114751971.jpg", 
  "imageData": null, 
  "imageHeight": 720, 
  "imageWidth": 1280
}